ctd_tools/__init__.py
ctd_tools/__main__.py
ctd_tools-0.3.0.dist-info/METADATA
ctd_tools-0.3.0.dist-info/WHEEL
ctd_tools-0.3.0.dist-info/entry_points.txt
ctd_tools-0.3.0.dist-info/top_level.txt
ctd_tools-0.3.0.dist-info/RECORD
